molgenis/bbmri_eric/__init__.py
molgenis/bbmri_eric/bbmri_client.py
molgenis/bbmri_eric/categories.py
molgenis/bbmri_eric/eric.py
molgenis/bbmri_eric/errors.py
molgenis/bbmri_eric/model.py
molgenis/bbmri_eric/model_fitting.py
molgenis/bbmri_eric/pid_manager.py
molgenis/bbmri_eric/pid_service.py
molgenis/bbmri_eric/printer.py
molgenis/bbmri_eric/publication_preparer.py
molgenis/bbmri_eric/publisher.py
molgenis/bbmri_eric/stager.py
molgenis/bbmri_eric/transformer.py
molgenis/bbmri_eric/utils.py
molgenis/bbmri_eric/validation.py
molgenis_py_bbmri_eric-1.18.1.dist-info/AUTHORS.md
molgenis_py_bbmri_eric-1.18.1.dist-info/LICENSE.txt
molgenis_py_bbmri_eric-1.18.1.dist-info/METADATA
molgenis_py_bbmri_eric-1.18.1.dist-info/WHEEL
molgenis_py_bbmri_eric-1.18.1.dist-info/top_level.txt
molgenis_py_bbmri_eric-1.18.1.dist-info/RECORD
