Metadata-Version: 2.1
Name: molgenis-py-bbmri-eric
Version: 1.18.1
Summary: MOLGENIS Python tooling for BBMRI-ERIC
Home-page: https://github.com/molgenis/molgenis-py-bbmri-eric
Author: Tommy de Boer
Author-email: t.de.boer01@umcg.nl
License: LGPL-3.0-only
Project-URL: Source, https://github.com/molgenis/molgenis-py-bbmri-eric
Platform: any
Classifier: License :: OSI Approved :: GNU Lesser General Public License v3 (LGPLv3)
Classifier: Programming Language :: Python
Classifier: Programming Language :: Python :: 3 :: Only
Classifier: Programming Language :: Python :: 3.10
Requires-Python: >=3.10
License-File: LICENSE.txt
License-File: AUTHORS.md
Requires-Dist: dataclasses
Requires-Dist: molgenis-py-client ==2.4.1
Requires-Dist: pyhandle >=1.1.0
Requires-Dist: requests >=2.21.0
Requires-Dist: unidecode
Provides-Extra: testing
Requires-Dist: setuptools ; extra == 'testing'
Requires-Dist: pytest ; extra == 'testing'
Requires-Dist: pytest-cov ; extra == 'testing'
